<?xml version="1.0" ?>
<all>
	<names>
		<fr>Viskuse</fr>
		<de>Quabbel</de>
		<it>Frillish</it>
		<en>Frillish</en>
	</names>
	<national_id>592</national_id>
	<types>
		<item>Water</item>
		<item>Ghost</item>
	</types>
	<abilities>
		<item>
			<name>Water Absorb</name>
		</item>
		<item>
			<name>Damp</name>
			<hidden>true</hidden>
		</item>
	</abilities>
	<gender_ratios>
		<male>50.0</male>
		<female>50.0</female>
	</gender_ratios>
	<catch_rate>190</catch_rate>
	<egg_groups>
		<item>Amorphous</item>
	</egg_groups>
	<hatch_time>
		<item>5355</item>
		<item>5609</item>
	</hatch_time>
	<height_us>3'11&quot;</height_us>
	<height_eu>1.2 m</height_eu>
	<weight_us>72.8 lbs.</weight_us>
	<weight_eu>33.0 kg</weight_eu>
	<base_exp_yield>67</base_exp_yield>
	<leveling_rate>Medium Fast</leveling_rate>
	<ev_yield>
		<hp>0</hp>
		<atk>0</atk>
		<def>0</def>
		<sp_atk>0</sp_atk>
		<sp_def>1</sp_def>
		<speed>0</speed>
	</ev_yield>
	<color>White</color>
	<base_friendship>70</base_friendship>
	<base_stats>
		<hp>55</hp>
		<atk>40</atk>
		<def>50</def>
		<sp_atk>65</sp_atk>
		<sp_def>85</sp_def>
		<speed>40</speed>
	</base_stats>
	<evolutions>
		<item>
			<to>Jellicent</to>
			<level>40</level>
		</item>
	</evolutions>
	<categories>
		<en>Floating Pokémon</en>
		<de>Gleit</de>
	</categories>
	<kanto_id/>
	<johto_id/>
	<hoenn_id/>
	<sinnoh_id/>
	<unova_id>98</unova_id>
	<kalos_id/>
	<alola_id/>
	<mega_evolutions/>
	<evolution_from/>
	<variations>
		<item>
			<condition>female</condition>
			<image_suffix>female</image_suffix>
			<names>
				<en>Female</en>
				<de>Weiblich</de>
			</names>
			<types>
				<item>Water</item>
				<item>Ghost</item>
			</types>
		</item>
	</variations>
	<pokedex_entries>
		<Black>
			<en>With its thin, veil-like arms wrapped around the body of its opponent, it sinks to the ocean floor.</en>
			<de>Schlingt seine dünnen, schleierartigen Arme um den Gegner und lässt sich mit ihm zum Meeresgrund sinken.</de>
		</Black>
		<White>
			<en>They paralyze prey with poison, then drag them down to their lairs, five miles below the surface.</en>
			<de>Es lähmt seine Beute mit Gift und verschleppt sie in seinen Unterschlupf, acht Kilometer unter dem Meeresspiegel.</de>
		</White>
		<Black_2>
			<en>If its veil-like arms stun and wrap a foe, that foe will be dragged miles below the surface, never to return.</en>
			<de>Es schlingt seine schleierartigen Arme um seine Beute und entführt sie 8 000 Meter in die Tiefe, wo es sie schließlich tötet.</de>
		</Black_2>
		<White_2>
			<en>If its veil-like arms stun and wrap a foe, that foe will be dragged miles below the surface, never to return.</en>
			<de>Es schlingt seine schleierartigen Arme um seine Beute und entführt sie 8 000 Meter in die Tiefe, wo es sie schließlich tötet.</de>
		</White_2>
		<X>
			<en>They paralyze prey with poison, then drag them down to their lairs, five miles below the surface.</en>
			<de>Es lähmt seine Beute mit Gift und verschleppt sie in seinen Unterschlupf, 8 km unter dem Meeresspiegel.</de>
		</X>
		<Y>
			<en>If its veil-like arms stun and wrap a foe, that foe will be dragged miles below the surface, never to return.</en>
			<de>Es schlingt seine schleierartigen Arme um seine Beute und entführt sie 8 000 m in die Tiefe, wo es sie schließlich tötet.</de>
		</Y>
		<Omega_Ruby>
			<en>They paralyze prey with poison, then drag them down to their lairs, five miles below the surface.</en>
			<de>Es schlingt seine schleierartigen Arme um seine Beute und entführt sie 8 000 m in die Tiefe, wo es sie schließlich tötet.</de>
		</Omega_Ruby>
		<Alpha_Sapphire>
			<en>If its veil-like arms stun and wrap a foe, that foe will be dragged miles below the surface, never to return.</en>
			<de>Es schlingt seine schleierartigen Arme um seine Beute und entführt sie 8 000 m in die Tiefe, wo es sie schließlich tötet.</de>
		</Alpha_Sapphire>
		<Ultra_Sun>
			<en>It wraps its veillike arms and legs around prey swimming by and drags them down to the depths of the ocean.</en>
			<de>Durch das Meer schwimmende Beute umschlingt es mit seinen schleierartigen Armen und zieht sie in die Tiefe.</de>
		</Ultra_Sun>
		<Ultra_Moon>
			<en>Using the invisible poison spikes on its veillike arms and legs, it paralyzes its enemies and causes them to drown.</en>
			<de>Mit bloßem Auge nicht sichtbare Giftstacheln bedecken seine schleierartigen Arme. Mit ihnen lähmt es seine Beute, bevor es sie ertränkt.</de>
		</Ultra_Moon>
	</pokedex_entries>
	<pokeathlon_stats>
		<speed>
			<item>0</item>
			<item>0</item>
		</speed>
		<power>
			<item>0</item>
			<item>0</item>
		</power>
		<stamina>
			<item>0</item>
			<item>0</item>
		</stamina>
		<skill>
			<item>0</item>
			<item>0</item>
		</skill>
		<jump>
			<item>0</item>
			<item>0</item>
		</jump>
	</pokeathlon_stats>
	<ultra_alola_id>139</ultra_alola_id>
	<move_learnsets>
		<item>
			<games>
				<item>Black</item>
				<item>White</item>
			</games>
			<learnset>
				<item>
					<move>Bubble</move>
					<level>1</level>
				</item>
				<item>
					<move>Water Sport</move>
					<level>1</level>
				</item>
				<item>
					<move>Absorb</move>
					<level>5</level>
				</item>
				<item>
					<move>Night Shade</move>
					<level>9</level>
				</item>
				<item>
					<move>Bubble Beam</move>
					<level>13</level>
				</item>
				<item>
					<move>Recover</move>
					<level>17</level>
				</item>
				<item>
					<move>Water Pulse</move>
					<level>22</level>
				</item>
				<item>
					<move>Ominous Wind</move>
					<level>27</level>
				</item>
				<item>
					<move>Brine</move>
					<level>32</level>
				</item>
				<item>
					<move>Rain Dance</move>
					<level>37</level>
				</item>
				<item>
					<move>Hex</move>
					<level>43</level>
				</item>
				<item>
					<move>Hydro Pump</move>
					<level>49</level>
				</item>
				<item>
					<move>Wring Out</move>
					<level>55</level>
				</item>
				<item>
					<move>Water Spout</move>
					<level>61</level>
				</item>
				<item>
					<move>Acid Armor</move>
					<egg_move>true</egg_move>
				</item>
				<item>
					<move>Confuse Ray</move>
					<egg_move>true</egg_move>
				</item>
				<item>
					<move>Constrict</move>
					<egg_move>true</egg_move>
				</item>
				<item>
					<move>Mist</move>
					<egg_move>true</egg_move>
				</item>
				<item>
					<move>Pain Split</move>
					<egg_move>true</egg_move>
				</item>
				<item>
					<move>Recover</move>
					<egg_move>true</egg_move>
				</item>
				<item>
					<move>Surf</move>
					<tm>HM3</tm>
				</item>
				<item>
					<move>Waterfall</move>
					<tm>HM5</tm>
				</item>
				<item>
					<move>Dive</move>
					<tm>HM6</tm>
				</item>
				<item>
					<move>Toxic</move>
					<tm>TM6</tm>
				</item>
				<item>
					<move>Hail</move>
					<tm>TM7</tm>
				</item>
				<item>
					<move>Hidden Power</move>
					<tm>TM10</tm>
				</item>
				<item>
					<move>Taunt</move>
					<tm>TM12</tm>
				</item>
				<item>
					<move>Ice Beam</move>
					<tm>TM13</tm>
				</item>
				<item>
					<move>Blizzard</move>
					<tm>TM14</tm>
				</item>
				<item>
					<move>Protect</move>
					<tm>TM17</tm>
				</item>
				<item>
					<move>Rain Dance</move>
					<tm>TM18</tm>
				</item>
				<item>
					<move>Safeguard</move>
					<tm>TM20</tm>
				</item>
				<item>
					<move>Frustration</move>
					<tm>TM21</tm>
				</item>
				<item>
					<move>Return</move>
					<tm>TM27</tm>
				</item>
				<item>
					<move>Psychic</move>
					<tm>TM29</tm>
				</item>
				<item>
					<move>Shadow Ball</move>
					<tm>TM30</tm>
				</item>
				<item>
					<move>Double Team</move>
					<tm>TM32</tm>
				</item>
				<item>
					<move>Sludge Wave</move>
					<tm>TM34</tm>
				</item>
				<item>
					<move>Sludge Bomb</move>
					<tm>TM36</tm>
				</item>
				<item>
					<move>Facade</move>
					<tm>TM42</tm>
				</item>
				<item>
					<move>Rest</move>
					<tm>TM44</tm>
				</item>
				<item>
					<move>Attract</move>
					<tm>TM45</tm>
				</item>
				<item>
					<move>Round</move>
					<tm>TM48</tm>
				</item>
				<item>
					<move>Energy Ball</move>
					<tm>TM53</tm>
				</item>
				<item>
					<move>Scald</move>
					<tm>TM55</tm>
				</item>
				<item>
					<move>Will-O-Wisp</move>
					<tm>TM61</tm>
				</item>
				<item>
					<move>Flash</move>
					<tm>TM70</tm>
				</item>
				<item>
					<move>Psych Up</move>
					<tm>TM77</tm>
				</item>
				<item>
					<move>Dream Eater</move>
					<tm>TM85</tm>
				</item>
				<item>
					<move>Swagger</move>
					<tm>TM87</tm>
				</item>
				<item>
					<move>Substitute</move>
					<tm>TM90</tm>
				</item>
				<item>
					<move>Trick Room</move>
					<tm>TM92</tm>
				</item>
			</learnset>
		</item>
		<item>
			<games>
				<item>Black 2</item>
				<item>White 2</item>
			</games>
			<learnset>
				<item>
					<move>Bubble</move>
					<level>1</level>
				</item>
				<item>
					<move>Water Sport</move>
					<level>1</level>
				</item>
				<item>
					<move>Absorb</move>
					<level>5</level>
				</item>
				<item>
					<move>Night Shade</move>
					<level>9</level>
				</item>
				<item>
					<move>Bubble Beam</move>
					<level>13</level>
				</item>
				<item>
					<move>Recover</move>
					<level>17</level>
				</item>
				<item>
					<move>Water Pulse</move>
					<level>22</level>
				</item>
				<item>
					<move>Ominous Wind</move>
					<level>27</level>
				</item>
				<item>
					<move>Brine</move>
					<level>32</level>
				</item>
				<item>
					<move>Rain Dance</move>
					<level>37</level>
				</item>
				<item>
					<move>Hex</move>
					<level>43</level>
				</item>
				<item>
					<move>Hydro Pump</move>
					<level>49</level>
				</item>
				<item>
					<move>Wring Out</move>
					<level>55</level>
				</item>
				<item>
					<move>Water Spout</move>
					<level>61</level>
				</item>
				<item>
					<move>Acid Armor</move>
					<egg_move>true</egg_move>
				</item>
				<item>
					<move>Confuse Ray</move>
					<egg_move>true</egg_move>
				</item>
				<item>
					<move>Constrict</move>
					<egg_move>true</egg_move>
				</item>
				<item>
					<move>Mist</move>
					<egg_move>true</egg_move>
				</item>
				<item>
					<move>Pain Split</move>
					<egg_move>true</egg_move>
				</item>
				<item>
					<move>Recover</move>
					<egg_move>true</egg_move>
				</item>
				<item>
					<move>Surf</move>
					<tm>HM3</tm>
				</item>
				<item>
					<move>Waterfall</move>
					<tm>HM5</tm>
				</item>
				<item>
					<move>Dive</move>
					<tm>HM6</tm>
				</item>
				<item>
					<move>Toxic</move>
					<tm>TM6</tm>
				</item>
				<item>
					<move>Hail</move>
					<tm>TM7</tm>
				</item>
				<item>
					<move>Hidden Power</move>
					<tm>TM10</tm>
				</item>
				<item>
					<move>Taunt</move>
					<tm>TM12</tm>
				</item>
				<item>
					<move>Ice Beam</move>
					<tm>TM13</tm>
				</item>
				<item>
					<move>Blizzard</move>
					<tm>TM14</tm>
				</item>
				<item>
					<move>Protect</move>
					<tm>TM17</tm>
				</item>
				<item>
					<move>Rain Dance</move>
					<tm>TM18</tm>
				</item>
				<item>
					<move>Safeguard</move>
					<tm>TM20</tm>
				</item>
				<item>
					<move>Frustration</move>
					<tm>TM21</tm>
				</item>
				<item>
					<move>Return</move>
					<tm>TM27</tm>
				</item>
				<item>
					<move>Psychic</move>
					<tm>TM29</tm>
				</item>
				<item>
					<move>Shadow Ball</move>
					<tm>TM30</tm>
				</item>
				<item>
					<move>Double Team</move>
					<tm>TM32</tm>
				</item>
				<item>
					<move>Sludge Wave</move>
					<tm>TM34</tm>
				</item>
				<item>
					<move>Sludge Bomb</move>
					<tm>TM36</tm>
				</item>
				<item>
					<move>Facade</move>
					<tm>TM42</tm>
				</item>
				<item>
					<move>Rest</move>
					<tm>TM44</tm>
				</item>
				<item>
					<move>Attract</move>
					<tm>TM45</tm>
				</item>
				<item>
					<move>Round</move>
					<tm>TM48</tm>
				</item>
				<item>
					<move>Energy Ball</move>
					<tm>TM53</tm>
				</item>
				<item>
					<move>Scald</move>
					<tm>TM55</tm>
				</item>
				<item>
					<move>Will-O-Wisp</move>
					<tm>TM61</tm>
				</item>
				<item>
					<move>Flash</move>
					<tm>TM70</tm>
				</item>
				<item>
					<move>Psych Up</move>
					<tm>TM77</tm>
				</item>
				<item>
					<move>Dream Eater</move>
					<tm>TM85</tm>
				</item>
				<item>
					<move>Swagger</move>
					<tm>TM87</tm>
				</item>
				<item>
					<move>Substitute</move>
					<tm>TM90</tm>
				</item>
				<item>
					<move>Trick Room</move>
					<tm>TM92</tm>
				</item>
			</learnset>
		</item>
		<item>
			<games>
				<item>X</item>
				<item>Y</item>
			</games>
			<learnset>
				<item>
					<move>Bubble</move>
					<level>1</level>
				</item>
				<item>
					<move>Water Sport</move>
					<level>1</level>
				</item>
				<item>
					<move>Absorb</move>
					<level>5</level>
				</item>
				<item>
					<move>Night Shade</move>
					<level>9</level>
				</item>
				<item>
					<move>Bubble Beam</move>
					<level>13</level>
				</item>
				<item>
					<move>Recover</move>
					<level>17</level>
				</item>
				<item>
					<move>Water Pulse</move>
					<level>22</level>
				</item>
				<item>
					<move>Ominous Wind</move>
					<level>27</level>
				</item>
				<item>
					<move>Brine</move>
					<level>32</level>
				</item>
				<item>
					<move>Rain Dance</move>
					<level>37</level>
				</item>
				<item>
					<move>Hex</move>
					<level>43</level>
				</item>
				<item>
					<move>Hydro Pump</move>
					<level>49</level>
				</item>
				<item>
					<move>Wring Out</move>
					<level>55</level>
				</item>
				<item>
					<move>Water Spout</move>
					<level>61</level>
				</item>
				<item>
					<move>Acid Armor</move>
					<egg_move>true</egg_move>
				</item>
				<item>
					<move>Confuse Ray</move>
					<egg_move>true</egg_move>
				</item>
				<item>
					<move>Constrict</move>
					<egg_move>true</egg_move>
				</item>
				<item>
					<move>Mist</move>
					<egg_move>true</egg_move>
				</item>
				<item>
					<move>Pain Split</move>
					<egg_move>true</egg_move>
				</item>
				<item>
					<move>Recover</move>
					<egg_move>true</egg_move>
				</item>
				<item>
					<move>Surf</move>
					<tm>HM3</tm>
				</item>
				<item>
					<move>Waterfall</move>
					<tm>HM5</tm>
				</item>
				<item>
					<move>Toxic</move>
					<tm>TM6</tm>
				</item>
				<item>
					<move>Hail</move>
					<tm>TM7</tm>
				</item>
				<item>
					<move>Hidden Power</move>
					<tm>TM10</tm>
				</item>
				<item>
					<move>Taunt</move>
					<tm>TM12</tm>
				</item>
				<item>
					<move>Ice Beam</move>
					<tm>TM13</tm>
				</item>
				<item>
					<move>Blizzard</move>
					<tm>TM14</tm>
				</item>
				<item>
					<move>Protect</move>
					<tm>TM17</tm>
				</item>
				<item>
					<move>Rain Dance</move>
					<tm>TM18</tm>
				</item>
				<item>
					<move>Safeguard</move>
					<tm>TM20</tm>
				</item>
				<item>
					<move>Frustration</move>
					<tm>TM21</tm>
				</item>
				<item>
					<move>Return</move>
					<tm>TM27</tm>
				</item>
				<item>
					<move>Psychic</move>
					<tm>TM29</tm>
				</item>
				<item>
					<move>Shadow Ball</move>
					<tm>TM30</tm>
				</item>
				<item>
					<move>Double Team</move>
					<tm>TM32</tm>
				</item>
				<item>
					<move>Sludge Wave</move>
					<tm>TM34</tm>
				</item>
				<item>
					<move>Sludge Bomb</move>
					<tm>TM36</tm>
				</item>
				<item>
					<move>Facade</move>
					<tm>TM42</tm>
				</item>
				<item>
					<move>Rest</move>
					<tm>TM44</tm>
				</item>
				<item>
					<move>Attract</move>
					<tm>TM45</tm>
				</item>
				<item>
					<move>Round</move>
					<tm>TM48</tm>
				</item>
				<item>
					<move>Energy Ball</move>
					<tm>TM53</tm>
				</item>
				<item>
					<move>Scald</move>
					<tm>TM55</tm>
				</item>
				<item>
					<move>Will-O-Wisp</move>
					<tm>TM61</tm>
				</item>
				<item>
					<move>Flash</move>
					<tm>TM70</tm>
				</item>
				<item>
					<move>Psych Up</move>
					<tm>TM77</tm>
				</item>
				<item>
					<move>Dream Eater</move>
					<tm>TM85</tm>
				</item>
				<item>
					<move>Swagger</move>
					<tm>TM87</tm>
				</item>
				<item>
					<move>Sleep Talk</move>
					<tm>TM88</tm>
				</item>
				<item>
					<move>Substitute</move>
					<tm>TM90</tm>
				</item>
				<item>
					<move>Trick Room</move>
					<tm>TM92</tm>
				</item>
				<item>
					<move>Dark Pulse</move>
					<tm>TM97</tm>
				</item>
				<item>
					<move>Dazzling Gleam</move>
					<tm>TM99</tm>
				</item>
				<item>
					<move>Confide</move>
					<tm>TM100</tm>
				</item>
			</learnset>
		</item>
		<item>
			<games>
				<item>Omega Ruby</item>
				<item>Alpha Sapphire</item>
			</games>
			<learnset>
				<item>
					<move>Bubble</move>
					<level>1</level>
				</item>
				<item>
					<move>Water Sport</move>
					<level>1</level>
				</item>
				<item>
					<move>Absorb</move>
					<level>5</level>
				</item>
				<item>
					<move>Night Shade</move>
					<level>9</level>
				</item>
				<item>
					<move>Bubble Beam</move>
					<level>13</level>
				</item>
				<item>
					<move>Recover</move>
					<level>17</level>
				</item>
				<item>
					<move>Water Pulse</move>
					<level>22</level>
				</item>
				<item>
					<move>Ominous Wind</move>
					<level>27</level>
				</item>
				<item>
					<move>Brine</move>
					<level>32</level>
				</item>
				<item>
					<move>Rain Dance</move>
					<level>37</level>
				</item>
				<item>
					<move>Hex</move>
					<level>43</level>
				</item>
				<item>
					<move>Hydro Pump</move>
					<level>49</level>
				</item>
				<item>
					<move>Wring Out</move>
					<level>55</level>
				</item>
				<item>
					<move>Water Spout</move>
					<level>61</level>
				</item>
				<item>
					<move>Acid Armor</move>
					<egg_move>true</egg_move>
				</item>
				<item>
					<move>Confuse Ray</move>
					<egg_move>true</egg_move>
				</item>
				<item>
					<move>Constrict</move>
					<egg_move>true</egg_move>
				</item>
				<item>
					<move>Mist</move>
					<egg_move>true</egg_move>
				</item>
				<item>
					<move>Pain Split</move>
					<egg_move>true</egg_move>
				</item>
				<item>
					<move>Recover</move>
					<egg_move>true</egg_move>
				</item>
				<item>
					<move>Surf</move>
					<tm>HM3</tm>
				</item>
				<item>
					<move>Waterfall</move>
					<tm>HM5</tm>
				</item>
				<item>
					<move>Dive</move>
					<tm>HM7</tm>
				</item>
				<item>
					<move>Toxic</move>
					<tm>TM6</tm>
				</item>
				<item>
					<move>Hail</move>
					<tm>TM7</tm>
				</item>
				<item>
					<move>Hidden Power</move>
					<tm>TM10</tm>
				</item>
				<item>
					<move>Taunt</move>
					<tm>TM12</tm>
				</item>
				<item>
					<move>Ice Beam</move>
					<tm>TM13</tm>
				</item>
				<item>
					<move>Blizzard</move>
					<tm>TM14</tm>
				</item>
				<item>
					<move>Protect</move>
					<tm>TM17</tm>
				</item>
				<item>
					<move>Rain Dance</move>
					<tm>TM18</tm>
				</item>
				<item>
					<move>Safeguard</move>
					<tm>TM20</tm>
				</item>
				<item>
					<move>Frustration</move>
					<tm>TM21</tm>
				</item>
				<item>
					<move>Return</move>
					<tm>TM27</tm>
				</item>
				<item>
					<move>Psychic</move>
					<tm>TM29</tm>
				</item>
				<item>
					<move>Shadow Ball</move>
					<tm>TM30</tm>
				</item>
				<item>
					<move>Double Team</move>
					<tm>TM32</tm>
				</item>
				<item>
					<move>Sludge Wave</move>
					<tm>TM34</tm>
				</item>
				<item>
					<move>Sludge Bomb</move>
					<tm>TM36</tm>
				</item>
				<item>
					<move>Facade</move>
					<tm>TM42</tm>
				</item>
				<item>
					<move>Rest</move>
					<tm>TM44</tm>
				</item>
				<item>
					<move>Attract</move>
					<tm>TM45</tm>
				</item>
				<item>
					<move>Round</move>
					<tm>TM48</tm>
				</item>
				<item>
					<move>Energy Ball</move>
					<tm>TM53</tm>
				</item>
				<item>
					<move>Scald</move>
					<tm>TM55</tm>
				</item>
				<item>
					<move>Will-O-Wisp</move>
					<tm>TM61</tm>
				</item>
				<item>
					<move>Flash</move>
					<tm>TM70</tm>
				</item>
				<item>
					<move>Psych Up</move>
					<tm>TM77</tm>
				</item>
				<item>
					<move>Dream Eater</move>
					<tm>TM85</tm>
				</item>
				<item>
					<move>Swagger</move>
					<tm>TM87</tm>
				</item>
				<item>
					<move>Sleep Talk</move>
					<tm>TM88</tm>
				</item>
				<item>
					<move>Substitute</move>
					<tm>TM90</tm>
				</item>
				<item>
					<move>Trick Room</move>
					<tm>TM92</tm>
				</item>
				<item>
					<move>Secret Power</move>
					<tm>TM94</tm>
				</item>
				<item>
					<move>Dark Pulse</move>
					<tm>TM97</tm>
				</item>
				<item>
					<move>Dazzling Gleam</move>
					<tm>TM99</tm>
				</item>
				<item>
					<move>Confide</move>
					<tm>TM100</tm>
				</item>
			</learnset>
		</item>
		<item>
			<games>
				<item>Sun</item>
				<item>Moon</item>
			</games>
			<learnset>
				<item>
					<move>Bubble</move>
					<level>1</level>
				</item>
				<item>
					<move>Water Sport</move>
					<level>1</level>
				</item>
				<item>
					<move>Absorb</move>
					<level>5</level>
				</item>
				<item>
					<move>Night Shade</move>
					<level>9</level>
				</item>
				<item>
					<move>Bubble Beam</move>
					<level>13</level>
				</item>
				<item>
					<move>Recover</move>
					<level>17</level>
				</item>
				<item>
					<move>Water Pulse</move>
					<level>22</level>
				</item>
				<item>
					<move>Ominous Wind</move>
					<level>27</level>
				</item>
				<item>
					<move>Brine</move>
					<level>32</level>
				</item>
				<item>
					<move>Rain Dance</move>
					<level>37</level>
				</item>
				<item>
					<move>Hex</move>
					<level>43</level>
				</item>
				<item>
					<move>Hydro Pump</move>
					<level>49</level>
				</item>
				<item>
					<move>Wring Out</move>
					<level>55</level>
				</item>
				<item>
					<move>Water Spout</move>
					<level>61</level>
				</item>
				<item>
					<move>Acid Armor</move>
					<egg_move>true</egg_move>
				</item>
				<item>
					<move>Confuse Ray</move>
					<egg_move>true</egg_move>
				</item>
				<item>
					<move>Constrict</move>
					<egg_move>true</egg_move>
				</item>
				<item>
					<move>Mist</move>
					<egg_move>true</egg_move>
				</item>
				<item>
					<move>Pain Split</move>
					<egg_move>true</egg_move>
				</item>
				<item>
					<move>Recover</move>
					<egg_move>true</egg_move>
				</item>
				<item>
					<move>Toxic</move>
					<tm>TM6</tm>
				</item>
				<item>
					<move>Hail</move>
					<tm>TM7</tm>
				</item>
				<item>
					<move>Hidden Power</move>
					<tm>TM10</tm>
				</item>
				<item>
					<move>Taunt</move>
					<tm>TM12</tm>
				</item>
				<item>
					<move>Ice Beam</move>
					<tm>TM13</tm>
				</item>
				<item>
					<move>Blizzard</move>
					<tm>TM14</tm>
				</item>
				<item>
					<move>Protect</move>
					<tm>TM17</tm>
				</item>
				<item>
					<move>Rain Dance</move>
					<tm>TM18</tm>
				</item>
				<item>
					<move>Safeguard</move>
					<tm>TM20</tm>
				</item>
				<item>
					<move>Frustration</move>
					<tm>TM21</tm>
				</item>
				<item>
					<move>Return</move>
					<tm>TM27</tm>
				</item>
				<item>
					<move>Psychic</move>
					<tm>TM29</tm>
				</item>
				<item>
					<move>Shadow Ball</move>
					<tm>TM30</tm>
				</item>
				<item>
					<move>Double Team</move>
					<tm>TM32</tm>
				</item>
				<item>
					<move>Sludge Wave</move>
					<tm>TM34</tm>
				</item>
				<item>
					<move>Sludge Bomb</move>
					<tm>TM36</tm>
				</item>
				<item>
					<move>Facade</move>
					<tm>TM42</tm>
				</item>
				<item>
					<move>Rest</move>
					<tm>TM44</tm>
				</item>
				<item>
					<move>Attract</move>
					<tm>TM45</tm>
				</item>
				<item>
					<move>Round</move>
					<tm>TM48</tm>
				</item>
				<item>
					<move>Energy Ball</move>
					<tm>TM53</tm>
				</item>
				<item>
					<move>Scald</move>
					<tm>TM55</tm>
				</item>
				<item>
					<move>Will-O-Wisp</move>
					<tm>TM61</tm>
				</item>
				<item>
					<move>Psych Up</move>
					<tm>TM77</tm>
				</item>
				<item>
					<move>Dream Eater</move>
					<tm>TM85</tm>
				</item>
				<item>
					<move>Swagger</move>
					<tm>TM87</tm>
				</item>
				<item>
					<move>Sleep Talk</move>
					<tm>TM88</tm>
				</item>
				<item>
					<move>Substitute</move>
					<tm>TM90</tm>
				</item>
				<item>
					<move>Trick Room</move>
					<tm>TM92</tm>
				</item>
				<item>
					<move>Surf</move>
					<tm>TM94</tm>
				</item>
				<item>
					<move>Dark Pulse</move>
					<tm>TM97</tm>
				</item>
				<item>
					<move>Waterfall</move>
					<tm>TM98</tm>
				</item>
				<item>
					<move>Dazzling Gleam</move>
					<tm>TM99</tm>
				</item>
				<item>
					<move>Confide</move>
					<tm>TM100</tm>
				</item>
			</learnset>
		</item>
		<item>
			<games>
				<item>Ultra Sun</item>
				<item>Ultra Moon</item>
			</games>
			<learnset>
				<item>
					<move>Bubble</move>
					<level>1</level>
				</item>
				<item>
					<move>Water Sport</move>
					<level>1</level>
				</item>
				<item>
					<move>Absorb</move>
					<level>5</level>
				</item>
				<item>
					<move>Night Shade</move>
					<level>9</level>
				</item>
				<item>
					<move>Bubble Beam</move>
					<level>13</level>
				</item>
				<item>
					<move>Recover</move>
					<level>17</level>
				</item>
				<item>
					<move>Water Pulse</move>
					<level>22</level>
				</item>
				<item>
					<move>Ominous Wind</move>
					<level>27</level>
				</item>
				<item>
					<move>Brine</move>
					<level>32</level>
				</item>
				<item>
					<move>Rain Dance</move>
					<level>37</level>
				</item>
				<item>
					<move>Hex</move>
					<level>43</level>
				</item>
				<item>
					<move>Hydro Pump</move>
					<level>49</level>
				</item>
				<item>
					<move>Wring Out</move>
					<level>55</level>
				</item>
				<item>
					<move>Water Spout</move>
					<level>61</level>
				</item>
				<item>
					<move>Acid Armor</move>
					<egg_move>true</egg_move>
				</item>
				<item>
					<move>Confuse Ray</move>
					<egg_move>true</egg_move>
				</item>
				<item>
					<move>Constrict</move>
					<egg_move>true</egg_move>
				</item>
				<item>
					<move>Mist</move>
					<egg_move>true</egg_move>
				</item>
				<item>
					<move>Pain Split</move>
					<egg_move>true</egg_move>
				</item>
				<item>
					<move>Recover</move>
					<egg_move>true</egg_move>
				</item>
				<item>
					<move>Toxic</move>
					<tm>TM6</tm>
				</item>
				<item>
					<move>Hail</move>
					<tm>TM7</tm>
				</item>
				<item>
					<move>Hidden Power</move>
					<tm>TM10</tm>
				</item>
				<item>
					<move>Taunt</move>
					<tm>TM12</tm>
				</item>
				<item>
					<move>Ice Beam</move>
					<tm>TM13</tm>
				</item>
				<item>
					<move>Blizzard</move>
					<tm>TM14</tm>
				</item>
				<item>
					<move>Protect</move>
					<tm>TM17</tm>
				</item>
				<item>
					<move>Rain Dance</move>
					<tm>TM18</tm>
				</item>
				<item>
					<move>Safeguard</move>
					<tm>TM20</tm>
				</item>
				<item>
					<move>Frustration</move>
					<tm>TM21</tm>
				</item>
				<item>
					<move>Return</move>
					<tm>TM27</tm>
				</item>
				<item>
					<move>Psychic</move>
					<tm>TM29</tm>
				</item>
				<item>
					<move>Shadow Ball</move>
					<tm>TM30</tm>
				</item>
				<item>
					<move>Double Team</move>
					<tm>TM32</tm>
				</item>
				<item>
					<move>Sludge Wave</move>
					<tm>TM34</tm>
				</item>
				<item>
					<move>Sludge Bomb</move>
					<tm>TM36</tm>
				</item>
				<item>
					<move>Facade</move>
					<tm>TM42</tm>
				</item>
				<item>
					<move>Rest</move>
					<tm>TM44</tm>
				</item>
				<item>
					<move>Attract</move>
					<tm>TM45</tm>
				</item>
				<item>
					<move>Round</move>
					<tm>TM48</tm>
				</item>
				<item>
					<move>Energy Ball</move>
					<tm>TM53</tm>
				</item>
				<item>
					<move>Scald</move>
					<tm>TM55</tm>
				</item>
				<item>
					<move>Will-O-Wisp</move>
					<tm>TM61</tm>
				</item>
				<item>
					<move>Psych Up</move>
					<tm>TM77</tm>
				</item>
				<item>
					<move>Dream Eater</move>
					<tm>TM85</tm>
				</item>
				<item>
					<move>Swagger</move>
					<tm>TM87</tm>
				</item>
				<item>
					<move>Sleep Talk</move>
					<tm>TM88</tm>
				</item>
				<item>
					<move>Substitute</move>
					<tm>TM90</tm>
				</item>
				<item>
					<move>Trick Room</move>
					<tm>TM92</tm>
				</item>
				<item>
					<move>Surf</move>
					<tm>TM94</tm>
				</item>
				<item>
					<move>Dark Pulse</move>
					<tm>TM97</tm>
				</item>
				<item>
					<move>Waterfall</move>
					<tm>TM98</tm>
				</item>
				<item>
					<move>Dazzling Gleam</move>
					<tm>TM99</tm>
				</item>
				<item>
					<move>Confide</move>
					<tm>TM100</tm>
				</item>
			</learnset>
		</item>
	</move_learnsets>
</all>
